hypycube/__init__.py
hypycube-0.0a0.dist-info/LICENSE
hypycube-0.0a0.dist-info/METADATA
hypycube-0.0a0.dist-info/WHEEL
hypycube-0.0a0.dist-info/top_level.txt
hypycube-0.0a0.dist-info/RECORD
